LICENSE.txt
README.md
setup.cfg
setup.py
ejelabs/Cracklabs.py
ejelabs/Main.py
ejelabs/__init__.py
ejelabs.egg-info/PKG-INFO
ejelabs.egg-info/SOURCES.txt
ejelabs.egg-info/dependency_links.txt
ejelabs.egg-info/requires.txt
ejelabs.egg-info/top_level.txt